{
  "slices": [
    {
      "id": "3458764656615997335",
      "slice": "slice: Create Todo List",
      "index": 1,
      "context": "TODO",
      "folder": "createtodolist",
      "status": "Planned"
    },
    {
      "id": "3458764656615997464",
      "slice": "slice: todo lists",
      "index": 3,
      "context": "TODO",
      "folder": "todolists",
      "status": "Planned"
    },
    {
      "id": "3458764656616164146",
      "slice": "slice: Add Todo Item",
      "index": 5,
      "context": "TODO",
      "folder": "addtodoitem",
      "status": "Planned"
    },
    {
      "id": "3458764656616164868",
      "slice": "slice: todo items",
      "index": 7,
      "context": "TODO",
      "folder": "todoitems",
      "status": "Planned"
    }
  ]
}